tviz/__init__.py
tviz/logger.py
tviz/adapters/__init__.py
tviz/adapters/tinker.py
tviz-0.2.2.dist-info/METADATA
tviz-0.2.2.dist-info/WHEEL
tviz-0.2.2.dist-info/RECORD
